bluetooth/__init__.py
bluetooth/add.py
bluetooth/cli.py
bluetooth/concurrency.py
bluetooth/exceptions.py
bluetooth/main.py
bluetooth/models.py
bluetooth/utils.py
bluetooth/bluetooth_peripherals/details.json
Bluetooth_Connect-0.1.dist-info/METADATA
Bluetooth_Connect-0.1.dist-info/WHEEL
Bluetooth_Connect-0.1.dist-info/entry_points.txt
Bluetooth_Connect-0.1.dist-info/top_level.txt
Bluetooth_Connect-0.1.dist-info/RECORD
