Metadata-Version: 1.0
Name: Bluetooth Connect
Version: 0.1
Summary: Connect Bluetooth Devices
Home-page: UNKNOWN
Author: Akhil <akhilgodvsdemon@gmail.com>
Author-email: UNKNOWN
License: MIT
Platform: UNKNOWN
